stork_search-0.1.0.dist-info/METADATA
stork_search-0.1.0.dist-info/WHEEL
stork_search-0.1.0.dist-info/license_files/LICENSE
stork_search/__init__.py
stork_search/stork_search.cpython-38-x86_64-linux-gnu.so
stork_search-0.1.0.dist-info/RECORD
